[
    {
        "PackageName": "Avalonia",
        "PackageVersion": "0.10.13",
        "PackageUrl": "https://avaloniaui.net/",
        "Copyright": "Copyright 2022 © The AvaloniaUI Project",
        "Authors": [
            "Avalonia"
        ],
        "Description": "Avalonia is a cross-platform UI framework for .NET providing a flexible styling system and supporting a wide range of Operating Systems such as Windows, Linux, MacOS and with experimental support for Android, iOS and WebAssembly.",
        "LicenseUrl": "https://licenses.nuget.org/MIT",
        "LicenseType": "MIT"
    },
    {
        "PackageName": "Avalonia.Desktop",
        "PackageVersion": "0.10.13",
        "PackageUrl": "https://avaloniaui.net/",
        "Copyright": "Copyright 2022 © The AvaloniaUI Project",
        "Authors": [
            "Avalonia.Desktop"
        ],
        "Description": "Avalonia is a cross-platform UI framework for .NET providing a flexible styling system and supporting a wide range of Operating Systems such as Windows, Linux, MacOS and with experimental support for Android, iOS and WebAssembly.",
        "LicenseUrl": "https://licenses.nuget.org/MIT",
        "LicenseType": "MIT"
    },
    {
        "PackageName": "Avalonia.Diagnostics",
        "PackageVersion": "0.10.13",
        "PackageUrl": "https://avaloniaui.net/",
        "Copyright": "Copyright 2022 © The AvaloniaUI Project",
        "Authors": [
            "Avalonia.Diagnostics"
        ],
        "Description": "Avalonia is a cross-platform UI framework for .NET providing a flexible styling system and supporting a wide range of Operating Systems such as Windows, Linux, MacOS and with experimental support for Android, iOS and WebAssembly.",
        "LicenseUrl": "https://licenses.nuget.org/MIT",
        "LicenseType": "MIT"
    },
    {
        "PackageName": "DryIoc.dll",
        "PackageVersion": "5.0.1",
        "PackageUrl": "https://github.com/dadhi/DryIoc",
        "Copyright": "Copyright © 2013-2022 Maksim Volkau",
        "Authors": [
            "Maksim Volkau"
        ],
        "Description": "DryIoc is fast, small, full-featured IoC Container for .NET",
        "LicenseUrl": "https://licenses.nuget.org/MIT",
        "LicenseType": "MIT"
    },
    {
        "PackageName": "Material.Avalonia",
        "PackageVersion": "2.5.1",
        "PackageUrl": "https://github.com/AvaloniaCommunity/Material.Avalonia",
        "Copyright": "",
        "Authors": [
            "Larymar",
            "SKProCH",
            "Appleneko2001"
        ],
        "Description": "This repository is a set of styles that will help you customize your application in an appropriate material design.",
        "LicenseUrl": "https://raw.githubusercontent.com/AvaloniaCommunity/Material.Avalonia/master/LICENSE",
        "LicenseType": ""
    },
    {
        "PackageName": "Material.Icons.Avalonia",
        "PackageVersion": "1.0.2",
        "PackageUrl": "https://github.com/AvaloniaUtils/Material.Icons.Avalonia/",
        "Copyright": "",
        "Authors": [
            "SKProCH"
        ],
        "Description": "Avalonia control for display material icons from Material.Icons",
        "LicenseUrl": "https://github.com/AvaloniaUtils/Material.Icons.Avalonia/blob/master/LICENSE",
        "LicenseType": ""
    },
    {
        "PackageName": "Microsoft.Extensions.Configuration.Binder",
        "PackageVersion": "6.0.0",
        "PackageUrl": "https://dot.net/",
        "Copyright": "© Microsoft Corporation. All rights reserved.",
        "Authors": [
            "Microsoft"
        ],
        "Description": "Functionality to bind an object to data in configuration providers for Microsoft.Extensions.Configuration.",
        "LicenseUrl": "https://licenses.nuget.org/MIT",
        "LicenseType": "MIT"
    },
    {
        "PackageName": "Microsoft.Extensions.Configuration.CommandLine",
        "PackageVersion": "6.0.0",
        "PackageUrl": "https://dot.net/",
        "Copyright": "© Microsoft Corporation. All rights reserved.",
        "Authors": [
            "Microsoft"
        ],
        "Description": "Command line configuration provider implementation for Microsoft.Extensions.Configuration.",
        "LicenseUrl": "https://licenses.nuget.org/MIT",
        "LicenseType": "MIT"
    },
    {
        "PackageName": "Microsoft.Extensions.Configuration.EnvironmentVariables",
        "PackageVersion": "6.0.1",
        "PackageUrl": "https://dot.net/",
        "Copyright": "© Microsoft Corporation. All rights reserved.",
        "Authors": [
            "Microsoft"
        ],
        "Description": "Environment variables configuration provider implementation for Microsoft.Extensions.Configuration.",
        "LicenseUrl": "https://licenses.nuget.org/MIT",
        "LicenseType": "MIT"
    },
    {
        "PackageName": "Microsoft.Extensions.Configuration.Json",
        "PackageVersion": "6.0.0",
        "PackageUrl": "https://dot.net/",
        "Copyright": "© Microsoft Corporation. All rights reserved.",
        "Authors": [
            "Microsoft"
        ],
        "Description": "JSON configuration provider implementation for Microsoft.Extensions.Configuration.",
        "LicenseUrl": "https://licenses.nuget.org/MIT",
        "LicenseType": "MIT"
    },
    {
        "PackageName": "Microsoft.Extensions.Configuration.UserSecrets",
        "PackageVersion": "6.0.1",
        "PackageUrl": "https://dot.net/",
        "Copyright": "© Microsoft Corporation. All rights reserved.",
        "Authors": [
            "Microsoft"
        ],
        "Description": "User secrets configuration provider implementation for Microsoft.Extensions.Configuration.",
        "LicenseUrl": "https://licenses.nuget.org/MIT",
        "LicenseType": "MIT"
    },
    {
        "PackageName": "Nerdbank.GitVersioning",
        "PackageVersion": "3.4.255",
        "PackageUrl": "https://github.com/dotnet/Nerdbank.GitVersioning",
        "Copyright": "",
        "Authors": [
            "Andrew Arnott"
        ],
        "Description": "Stamps your assemblies with semver 2.0 compliant git commit specific version information and provides NuGet versioning information as well.",
        "LicenseUrl": "https://licenses.nuget.org/MIT",
        "LicenseType": "MIT"
    }
]
